pyransame/__init__.py
pyransame/_version.py
pyransame/line.py
pyransame/py.typed
pyransame/surface.py
pyransame/util.py
pyransame/vertex.py
pyransame/volume.py
pyransame-0.4.0.dist-info/LICENSE
pyransame-0.4.0.dist-info/METADATA
pyransame-0.4.0.dist-info/WHEEL
pyransame-0.4.0.dist-info/top_level.txt
pyransame-0.4.0.dist-info/RECORD
