Metadata-Version: 2.1
Name: pyransame
Version: 0.4.0
Summary: PYthon RAndom SAmpling for MEshes
Author-email: Matthew Flamm <matthewhflamm0@gmail.com>
License: MIT License
Project-URL: Repository, https://github.com/MatthewFlamm/pyransame
Project-URL: Bug Tracker, https://github.com/MatthewFlamm/pyransame/issues
Project-URL: Documentation, https://matthewflamm.github.io/pyransame/
Keywords: pyvista,vtk,numpy,mesh,sample
Classifier: Programming Language :: Python :: 3
Classifier: Development Status :: 4 - Beta
Classifier: License :: OSI Approved :: MIT License
Requires-Python: >=3.8
License-File: LICENSE
Requires-Dist: pyvista >=0.44
Requires-Dist: numpy
